alibabacloud_opensearch20171225/__init__.py
alibabacloud_opensearch20171225/client.py
alibabacloud_opensearch20171225/models/__init__.py
alibabacloud_opensearch20171225/models/_abtest_experiment.py
alibabacloud_opensearch20171225/models/_abtest_group.py
alibabacloud_opensearch20171225/models/_abtest_scene.py
alibabacloud_opensearch20171225/models/_app.py
alibabacloud_opensearch20171225/models/_app_group.py
alibabacloud_opensearch20171225/models/_bind_es_instance_request.py
alibabacloud_opensearch20171225/models/_bind_es_instance_response.py
alibabacloud_opensearch20171225/models/_bind_es_instance_response_body.py
alibabacloud_opensearch20171225/models/_bind_esuser_analyzer_request.py
alibabacloud_opensearch20171225/models/_bind_esuser_analyzer_response.py
alibabacloud_opensearch20171225/models/_bind_esuser_analyzer_response_body.py
alibabacloud_opensearch20171225/models/_compile_sort_script_response.py
alibabacloud_opensearch20171225/models/_compile_sort_script_response_body.py
alibabacloud_opensearch20171225/models/_create_abtest_experiment_request.py
alibabacloud_opensearch20171225/models/_create_abtest_experiment_response.py
alibabacloud_opensearch20171225/models/_create_abtest_experiment_response_body.py
alibabacloud_opensearch20171225/models/_create_abtest_group_request.py
alibabacloud_opensearch20171225/models/_create_abtest_group_response.py
alibabacloud_opensearch20171225/models/_create_abtest_group_response_body.py
alibabacloud_opensearch20171225/models/_create_abtest_scene_request.py
alibabacloud_opensearch20171225/models/_create_abtest_scene_response.py
alibabacloud_opensearch20171225/models/_create_abtest_scene_response_body.py
alibabacloud_opensearch20171225/models/_create_app_group_credentials_request.py
alibabacloud_opensearch20171225/models/_create_app_group_credentials_response.py
alibabacloud_opensearch20171225/models/_create_app_group_credentials_response_body.py
alibabacloud_opensearch20171225/models/_create_app_group_request.py
alibabacloud_opensearch20171225-5.0.0.dist-info/LICENSE
alibabacloud_opensearch20171225-5.0.0.dist-info/METADATA
alibabacloud_opensearch20171225-5.0.0.dist-info/WHEEL
alibabacloud_opensearch20171225-5.0.0.dist-info/top_level.txt
alibabacloud_opensearch20171225-5.0.0.dist-info/RECORD
